streamlit_pills_multiselect/__init__.py
streamlit_pills_multiselect/frontend/.env
streamlit_pills_multiselect/frontend/.prettierrc
streamlit_pills_multiselect/frontend/build/asset-manifest.json
streamlit_pills_multiselect/frontend/build/index.html
streamlit_pills_multiselect/frontend/build/precache-manifest.03d8768747f85fa123f5cfab96edbf06.js
streamlit_pills_multiselect/frontend/build/service-worker.js
streamlit_pills_multiselect/frontend/build/static/js/2.9e1583f4.chunk.js
streamlit_pills_multiselect/frontend/build/static/js/2.9e1583f4.chunk.js.LICENSE.txt
streamlit_pills_multiselect/frontend/build/static/js/2.9e1583f4.chunk.js.map
streamlit_pills_multiselect/frontend/build/static/js/main.ff7c57c2.chunk.js
streamlit_pills_multiselect/frontend/build/static/js/main.ff7c57c2.chunk.js.map
streamlit_pills_multiselect/frontend/build/static/js/runtime-main.ff189e23.js
streamlit_pills_multiselect/frontend/build/static/js/runtime-main.ff189e23.js.map
streamlit_pills_multiselect/frontend/build/styles.css
streamlit_pills_multiselect/frontend/package-lock.json
streamlit_pills_multiselect/frontend/package.json
streamlit_pills_multiselect/frontend/public/index.html
streamlit_pills_multiselect/frontend/public/styles.css
streamlit_pills_multiselect/frontend/src/index.tsx
streamlit_pills_multiselect/frontend/src/react-app-env.d.ts
streamlit_pills_multiselect/frontend/tsconfig.json
streamlit_pills_multiselect-0.6.1.dist-info/LICENSE
streamlit_pills_multiselect-0.6.1.dist-info/METADATA
streamlit_pills_multiselect-0.6.1.dist-info/WHEEL
streamlit_pills_multiselect-0.6.1.dist-info/RECORD
